pocaduck/__init__.py
pocaduck/ingestor.py
pocaduck/query.py
pocaduck/storage_config.py
pocaduck-0.1.1.dist-info/licenses/LICENSE
pocaduck-0.1.1.dist-info/METADATA
pocaduck-0.1.1.dist-info/WHEEL
pocaduck-0.1.1.dist-info/top_level.txt
pocaduck-0.1.1.dist-info/RECORD
