Metadata-Version: 2.4
Name: pocaduck
Version: 0.1.1
Summary: Efficient storage and retrieval of point clouds using Arrow ecosystem and DuckDB
Author-email: William Katz <katzw@hhmi.org>
License: BSD-3-Clause
Project-URL: Homepage, https://github.com/JaneliaSciComp/pocaduck
Classifier: Programming Language :: Python :: 3
Classifier: License :: OSI Approved :: BSD License
Classifier: Operating System :: OS Independent
Requires-Python: >=3.10
License-File: LICENSE
Requires-Dist: numpy>=1.26.4
Requires-Dist: pandas>=2.2.3
Requires-Dist: duckdb>=1.2.2
Requires-Dist: pyarrow>=16.1.0
Provides-Extra: dev
Requires-Dist: vastdb>=1.3.10; extra == "dev"
Requires-Dist: pytest>=6.0.0; extra == "dev"
Dynamic: license-file
